nltkor/Kor_char.py
nltkor/__init__.py
nltkor/etc.py
nltkor/lazyimport.py
nltkor/make_requirement.py
nltkor/trans.py
nltkor/alignment/__init__.py
nltkor/cider/__init__.py
nltkor/cider/cider.py
nltkor/cider/cider_scorer.py
nltkor/distance/__init__.py
nltkor/distance/wasserstein.py
nltkor/metrics/__init__.py
nltkor/metrics/bartscore.py
nltkor/metrics/bertscore.py
nltkor/metrics/classical.py
nltkor/metrics/entment.py
nltkor/metrics/eval.py
nltkor/metrics/mauve.py
nltkor/metrics/mauve_utils.py
nltkor/misc/__init__.py
nltkor/misc/string2string_basic_functions.py
nltkor/misc/string2string_default_tokenizer.py
nltkor/misc/string2string_hash_functions.py
nltkor/misc/string2string_word_embeddings.py
nltkor/search/__init__.py
nltkor/search/classical.py
nltkor/search/faiss_search.py
nltkor/search/kobert_tokenizer.py
nltkor/search/trie_search.py
nltkor/sejong/__init__.py
nltkor/sejong/ch.py
nltkor/sejong/dict_semClassNum.txt
nltkor/sejong/layer.txt
nltkor/sejong/sejong_download.py
nltkor/sejong/ssem.py
nltkor/sejong/__pycache__/__init__.cpython-38.pyc
nltkor/sejong/__pycache__/__init__.cpython-39.pyc
nltkor/sejong/__pycache__/sejong_download.cpython-38.pyc
nltkor/sejong/__pycache__/sejong_download.cpython-39.pyc
nltkor/sejong/__pycache__/ssem.cpython-38.pyc
nltkor/sejong/__pycache__/ssem.cpython-39.pyc
nltkor/similarity/__init__.py
nltkor/similarity/bartscore____.py
nltkor/similarity/bertscore____.py
nltkor/similarity/classical.py
nltkor/similarity/cosine_similarity.py
nltkor/tag/__init__.py
nltkor/tag/espresso_tag.py
nltkor/tag/__pycache__/__init__.cpython-38.pyc
nltkor/tag/__pycache__/__init__.cpython-39.pyc
nltkor/tag/__pycache__/espresso_tag.cpython-38.pyc
nltkor/tag/__pycache__/espresso_tag.cpython-39.pyc
nltkor/tag/libs/__init__.py
nltkor/tag/libs/arguments.py
nltkor/tag/libs/attributes.py
nltkor/tag/libs/config.py
nltkor/tag/libs/metadata.py
nltkor/tag/libs/network.c
nltkor/tag/libs/network.cpython-39-darwin.so
nltkor/tag/libs/network.pyx
nltkor/tag/libs/networkconv.pyx
nltkor-1.2.25.dist-info/LICENSE.txt
nltkor-1.2.25.dist-info/METADATA
nltkor-1.2.25.dist-info/WHEEL
nltkor-1.2.25.dist-info/top_level.txt
nltkor-1.2.25.dist-info/RECORD
