Metadata-Version: 2.1
Name: nltkor
Version: 1.2.25
Summary: UNKNOWN
Home-page: https://modi.changwon.ac.kr/air_cwnu/nlp_tool/nltk_ko.git
License: UNKNOWN
Keywords: string matching,pattern matching,edit distance,string to string correction,string to string matching,Levenshtein edit distance,Hamming distance,Damerau-Levenshtein distance,Jaro-Winkler distance,longest common subsequence,longest common substring,dynamic programming,approximate string matching,semantic similarity,natural language processing,NLP,information retrieval,rouge,sacrebleu,bertscore,bartscore,fasttext,glove,cosine similarity,Smith-Waterman,Needleman-Wunsch,Hirschberg,Karp-Rabi
Platform: UNKNOWN
Classifier: Programming Language :: Python :: 3.7
Classifier: Programming Language :: Python :: 3.8
Classifier: Programming Language :: Python :: 3.9
Classifier: Programming Language :: Python :: 3.10
Classifier: License :: OSI Approved :: MIT License
Classifier: Operating System :: OS Independent
Classifier: Typing :: Typed
Requires-Python: >=3.7
License-File: LICENSE.txt
Requires-Dist: Cython
Requires-Dist: numpy (<=1.26.4,>=1.23.5)
Requires-Dist: regex
Requires-Dist: tqdm (>=4.40.0)
Requires-Dist: joblib
Requires-Dist: requests
Requires-Dist: nltk (>3.0)
Requires-Dist: pyarrow
Requires-Dist: beautifulSoup4
Requires-Dist: faiss-cpu (==1.7.3)
Requires-Dist: datasets
Requires-Dist: torch
Requires-Dist: dill (<0.3.9)
Requires-Dist: scikit-learn (>=0.22.1)
Requires-Dist: transformers (==4.42.2)
Requires-Dist: protobuf
Requires-Dist: sentencepiece
Requires-Dist: pandas
Requires-Dist: bert-score
Requires-Dist: chardet
Requires-Dist: GPUtil
Requires-Dist: fasttext
